serviceultractl-0.2.0.dist-info/WHEEL
serviceultractl-0.2.0.dist-info/RECORD
serviceultractl-0.2.0.dist-info/top_level.txt
serviceultractl-0.2.0.dist-info/METADATA
serviceultractl-0.2.0.dist-info/zip-safe
serviceultractl-0.2.0.dist-info/DESCRIPTION.rst
serviceultractl-0.2.0.dist-info/entry_points.txt
serviceultractl-0.2.0.dist-info/metadata.json
serviceultractl/exportcommands.py
serviceultractl/__init__.py
serviceultractl/undeploycommands.py
serviceultractl/statiscommands.py
serviceultractl/stopcommands.py
serviceultractl/lscommands.py
serviceultractl/uploadcommands.py
serviceultractl/copycommands.py
serviceultractl/movecommands.py
serviceultractl/renamecommands.py
serviceultractl/downloadcommands.py
serviceultractl/client.py
serviceultractl/shell.py
serviceultractl/importcommands.py
serviceultractl/redeploycommands.py
serviceultractl/removecommands.py
serviceultractl/deletecommands.py
serviceultractl/deploycommands.py
serviceultractl/startcommands.py
serviceultractl/addcommands.py
serviceultractl/v3_0/__init__.py
serviceultractl/v3_0/cluster_en.py
serviceultractl/v3_0/commonnode.py
serviceultractl/v3_0/application.py
serviceultractl/v3_0/task.py
serviceultractl/v3_0/service.py
serviceultractl/v3_0/my_application_json.py
serviceultractl/v3_0/microservice_json.py
serviceultractl/v3_0/my_application_ch.py
serviceultractl/v3_0/application_ch.py
serviceultractl/v3_0/cluster.py
serviceultractl/v3_0/httpclient.py
serviceultractl/v3_0/task_json.py
serviceultractl/v3_0/microservice_ch.py
serviceultractl/v3_0/file_ch.py
serviceultractl/v3_0/my_application_en.py
serviceultractl/v3_0/task_ch.py
serviceultractl/v3_0/cluster_ch.py
serviceultractl/v3_0/application_json.py
serviceultractl/v3_0/service_ch.py
serviceultractl/v3_0/my_application.py
serviceultractl/v3_0/instance.py
serviceultractl/v3_0/commonnode_json.py
serviceultractl/v3_0/commonnode_ch.py
serviceultractl/v3_0/instance_json.py
serviceultractl/v3_0/microservice.py
serviceultractl/v3_0/task_en.py
serviceultractl/v3_0/file_json.py
serviceultractl/v3_0/instance_ch.py
serviceultractl/v3_0/instance_en.py
serviceultractl/v3_0/file.py
serviceultractl/v3_0/cluster_json.py
serviceultractl/v3_0/file_en.py
serviceultractl/v3_0/service_json.py
serviceultractl/v3_0/microservice_en.py
