Metadata-Version: 2.0
Name: serviceultractl
Version: 0.2.0
Summary: a tiny and smart cli player of dataultra based on Python
Home-page: http://demo.su.huayun.com/
Author: su
Author-email: du@huayun.com
License: MIT
Keywords: python serviceultra su.cli terminal
Platform: UNKNOWN
Requires-Dist: requests
Requires-Dist: prettytable
Requires-Dist: requests-toolbelt
